HISTORY.md
MANIFEST.in
README.md
requirements.txt
setup.cfg
setup.py
versioneer.py
py_handoff/__init__.py
py_handoff/_version.py
py_handoff/main.py
py_handoff.egg-info/PKG-INFO
py_handoff.egg-info/SOURCES.txt
py_handoff.egg-info/dependency_links.txt
py_handoff.egg-info/entry_points.txt
py_handoff.egg-info/not-zip-safe
py_handoff.egg-info/requires.txt
py_handoff.egg-info/top_level.txt